odoo/addons/l10n_th_company_novat/README.rst
odoo/addons/l10n_th_company_novat/__init__.py
odoo/addons/l10n_th_company_novat/__manifest__.py
odoo/addons/l10n_th_company_novat/i18n/l10n_th_company_novat.pot
odoo/addons/l10n_th_company_novat/models/__init__.py
odoo/addons/l10n_th_company_novat/models/account_move.py
odoo/addons/l10n_th_company_novat/models/hr_expense.py
odoo/addons/l10n_th_company_novat/models/partner.py
odoo/addons/l10n_th_company_novat/models/purchase.py
odoo/addons/l10n_th_company_novat/models/res_company.py
odoo/addons/l10n_th_company_novat/models/sale.py
odoo/addons/l10n_th_company_novat/readme/CONFIGURATION.rst
odoo/addons/l10n_th_company_novat/readme/CONTRIBUTORS.rst
odoo/addons/l10n_th_company_novat/readme/DESCRIPTION.rst
odoo/addons/l10n_th_company_novat/static/description/icon.png
odoo/addons/l10n_th_company_novat/static/description/index.html
odoo/addons/l10n_th_company_novat/tests/__init__.py
odoo/addons/l10n_th_company_novat/tests/test_company_novat.py
odoo/addons/l10n_th_company_novat/views/account_move_view.xml
odoo/addons/l10n_th_company_novat/views/hr_expense_view.xml
odoo/addons/l10n_th_company_novat/views/res_company_view.xml
odoo/addons/l10n_th_company_novat/views/res_partner_view.xml
odoo14_addon_l10n_th_company_novat-14.0.1.1.0.dist-info/METADATA
odoo14_addon_l10n_th_company_novat-14.0.1.1.0.dist-info/WHEEL
odoo14_addon_l10n_th_company_novat-14.0.1.1.0.dist-info/top_level.txt
odoo14_addon_l10n_th_company_novat-14.0.1.1.0.dist-info/RECORD
